AUTHORS
CHANGELOG
COPYING
MANIFEST.in
README
setup.py
clan/__init__.py
clan/auth.py
clan/diff.py
clan/report.py
clan/utils.py
clan.egg-info/PKG-INFO
clan.egg-info/SOURCES.txt
clan.egg-info/dependency_links.txt
clan.egg-info/entry_points.txt
clan.egg-info/requires.txt
clan.egg-info/top_level.txt
clan/templates/__init__.py
clan/templates/bootstrap.min.css
clan/templates/diff.html
clan/templates/report.html
clan/templates/styles.css